{
  "date": "2025-08-16",
  "generated_at": "2025-08-17T13:51:28.638744",
  "betting_lines": {
    "total_runs_line": 9.5,
    "moneyline_threshold": 0.52,
    "total_runs_threshold": 0.51
  },
  "games": {
    "Pittsburgh Pirates @ Chicago Cubs": {
      "away_team": "Pittsburgh Pirates",
      "home_team": "Chicago Cubs",
      "away_pitcher": "Mike Burrows",
      "home_pitcher": "Shota Imanaga",
      "has_tbd_pitchers": false,
      "predicted_score": "5.2-5.5",
      "predicted_total_runs": 10.7,
      "win_probabilities": {
        "away_prob": 0.471,
        "home_prob": 0.529
      },
      "betting_recommendations": {
        "moneyline": {
          "pick": "home",
          "team": "Chicago Cubs",
          "confidence": 0.529
        },
        "total_runs": {
          "line": 9.5,
          "pick": "over",
          "predicted_total": 10.7,
          "confidence": 0.538
        },
        "value_bets": [
          {
            "type": "moneyline",
            "recommendation": "Chicago Cubs ML",
            "expected_value": 0.058,
            "win_probability": 0.529,
            "american_odds": 110,
            "confidence": "medium"
          },
          {
            "type": "total",
            "recommendation": "Over 9.5",
            "expected_value": 0.076,
            "win_probability": 0.5378947368421052,
            "american_odds": -110,
            "confidence": "medium",
            "predicted_total": 10.7,
            "betting_line": 9.5
          }
        ]
      },
      "overall_confidence": 0.538,
      "recommendation_quality": "MEDIUM"
    },
    "Texas Rangers @ Toronto Blue Jays": {
      "away_team": "Texas Rangers",
      "home_team": "Toronto Blue Jays",
      "away_pitcher": "Patrick Corbin",
      "home_pitcher": "Eric Lauer",
      "has_tbd_pitchers": false,
      "predicted_score": "3.3-3.4",
      "predicted_total_runs": 6.7,
      "win_probabilities": {
        "away_prob": 0.472,
        "home_prob": 0.528
      },
      "betting_recommendations": {
        "moneyline": {
          "pick": "home",
          "team": "Toronto Blue Jays",
          "confidence": 0.528
        },
        "total_runs": {
          "line": 9.5,
          "pick": "under",
          "predicted_total": 6.7,
          "confidence": 0.588
        },
        "value_bets": [
          {
            "type": "moneyline",
            "recommendation": "Toronto Blue Jays ML",
            "expected_value": 0.056,
            "win_probability": 0.528,
            "american_odds": 110,
            "confidence": "medium"
          },
          {
            "type": "total",
            "recommendation": "Under 9.5",
            "expected_value": 0.177,
            "win_probability": 0.588421052631579,
            "american_odds": -110,
            "confidence": "medium",
            "predicted_total": 6.7,
            "betting_line": 9.5
          }
        ]
      },
      "overall_confidence": 0.588,
      "recommendation_quality": "MEDIUM"
    },
    "Philadelphia Phillies @ Washington Nationals": {
      "away_team": "Philadelphia Phillies",
      "home_team": "Washington Nationals",
      "away_pitcher": "Taijuan Walker",
      "home_pitcher": "Cade Cavalli",
      "has_tbd_pitchers": false,
      "predicted_score": "5.2-5.6",
      "predicted_total_runs": 10.8,
      "win_probabilities": {
        "away_prob": 0.458,
        "home_prob": 0.542
      },
      "betting_recommendations": {
        "moneyline": {
          "pick": "home",
          "team": "Washington Nationals",
          "confidence": 0.542
        },
        "total_runs": {
          "line": 9.5,
          "pick": "over",
          "predicted_total": 10.8,
          "confidence": 0.541
        },
        "value_bets": [
          {
            "type": "moneyline",
            "recommendation": "Washington Nationals ML",
            "expected_value": 0.084,
            "win_probability": 0.542,
            "american_odds": 110,
            "confidence": "medium"
          },
          {
            "type": "total",
            "recommendation": "Over 9.5",
            "expected_value": 0.082,
            "win_probability": 0.5410526315789473,
            "american_odds": -110,
            "confidence": "medium",
            "predicted_total": 10.8,
            "betting_line": 9.5
          }
        ]
      },
      "overall_confidence": 0.542,
      "recommendation_quality": "MEDIUM"
    },
    "Seattle Mariners @ New York Mets": {
      "away_team": "Seattle Mariners",
      "home_team": "New York Mets",
      "away_pitcher": "Bryan Woo",
      "home_pitcher": "Nolan McLean",
      "has_tbd_pitchers": false,
      "predicted_score": "5.3-5.6",
      "predicted_total_runs": 10.9,
      "win_probabilities": {
        "away_prob": 0.468,
        "home_prob": 0.532
      },
      "betting_recommendations": {
        "moneyline": {
          "pick": "home",
          "team": "New York Mets",
          "confidence": 0.532
        },
        "total_runs": {
          "line": 9.5,
          "pick": "over",
          "predicted_total": 10.9,
          "confidence": 0.544
        },
        "value_bets": [
          {
            "type": "moneyline",
            "recommendation": "New York Mets ML",
            "expected_value": 0.064,
            "win_probability": 0.532,
            "american_odds": 110,
            "confidence": "medium"
          },
          {
            "type": "total",
            "recommendation": "Over 9.5",
            "expected_value": 0.088,
            "win_probability": 0.5442105263157895,
            "american_odds": -110,
            "confidence": "medium",
            "predicted_total": 10.9,
            "betting_line": 9.5
          }
        ]
      },
      "overall_confidence": 0.544,
      "recommendation_quality": "MEDIUM"
    },
    "Miami Marlins @ Boston Red Sox": {
      "away_team": "Miami Marlins",
      "home_team": "Boston Red Sox",
      "away_pitcher": "Cal Quantrill",
      "home_pitcher": "Brayan Bello",
      "has_tbd_pitchers": false,
      "predicted_score": "3.3-3.4",
      "predicted_total_runs": 6.7,
      "win_probabilities": {
        "away_prob": 0.474,
        "home_prob": 0.526
      },
      "betting_recommendations": {
        "moneyline": {
          "pick": "home",
          "team": "Boston Red Sox",
          "confidence": 0.526
        },
        "total_runs": {
          "line": 9.5,
          "pick": "under",
          "predicted_total": 6.7,
          "confidence": 0.588
        },
        "value_bets": [
          {
            "type": "moneyline",
            "recommendation": "Boston Red Sox ML",
            "expected_value": 0.052,
            "win_probability": 0.526,
            "american_odds": 110,
            "confidence": "medium"
          },
          {
            "type": "total",
            "recommendation": "Under 9.5",
            "expected_value": 0.177,
            "win_probability": 0.588421052631579,
            "american_odds": -110,
            "confidence": "medium",
            "predicted_total": 6.7,
            "betting_line": 9.5
          }
        ]
      },
      "overall_confidence": 0.588,
      "recommendation_quality": "MEDIUM"
    },
    "Milwaukee Brewers @ Cincinnati Reds": {
      "away_team": "Milwaukee Brewers",
      "home_team": "Cincinnati Reds",
      "away_pitcher": "Quinn Priester",
      "home_pitcher": "Zack Littell",
      "has_tbd_pitchers": false,
      "predicted_score": "4.3-4.5",
      "predicted_total_runs": 8.8,
      "win_probabilities": {
        "away_prob": 0.463,
        "home_prob": 0.537
      },
      "betting_recommendations": {
        "moneyline": {
          "pick": "home",
          "team": "Cincinnati Reds",
          "confidence": 0.537
        },
        "total_runs": {
          "line": 9.5,
          "pick": "under",
          "predicted_total": 8.8,
          "confidence": 0.522
        },
        "value_bets": [
          {
            "type": "moneyline",
            "recommendation": "Cincinnati Reds ML",
            "expected_value": 0.074,
            "win_probability": 0.537,
            "american_odds": 110,
            "confidence": "medium"
          },
          {
            "type": "total",
            "recommendation": "Under 9.5",
            "expected_value": 0.044,
            "win_probability": 0.5221052631578947,
            "american_odds": -110,
            "confidence": "medium",
            "predicted_total": 8.8,
            "betting_line": 9.5
          }
        ]
      },
      "overall_confidence": 0.537,
      "recommendation_quality": "MEDIUM"
    },
    "Baltimore Orioles @ Houston Astros": {
      "away_team": "Baltimore Orioles",
      "home_team": "Houston Astros",
      "away_pitcher": "Rico Garcia",
      "home_pitcher": "Jason Alexander",
      "has_tbd_pitchers": false,
      "predicted_score": "5.2-5.6",
      "predicted_total_runs": 10.8,
      "win_probabilities": {
        "away_prob": 0.463,
        "home_prob": 0.537
      },
      "betting_recommendations": {
        "moneyline": {
          "pick": "home",
          "team": "Houston Astros",
          "confidence": 0.537
        },
        "total_runs": {
          "line": 9.5,
          "pick": "over",
          "predicted_total": 10.8,
          "confidence": 0.541
        },
        "value_bets": [
          {
            "type": "moneyline",
            "recommendation": "Houston Astros ML",
            "expected_value": 0.074,
            "win_probability": 0.537,
            "american_odds": 110,
            "confidence": "medium"
          },
          {
            "type": "total",
            "recommendation": "Over 9.5",
            "expected_value": 0.082,
            "win_probability": 0.5410526315789473,
            "american_odds": -110,
            "confidence": "medium",
            "predicted_total": 10.8,
            "betting_line": 9.5
          }
        ]
      },
      "overall_confidence": 0.541,
      "recommendation_quality": "MEDIUM"
    },
    "Atlanta Braves @ Cleveland Guardians": {
      "away_team": "Atlanta Braves",
      "home_team": "Cleveland Guardians",
      "away_pitcher": "Joey Wentz",
      "home_pitcher": "Slade Cecconi",
      "has_tbd_pitchers": false,
      "predicted_score": "5.3-5.5",
      "predicted_total_runs": 10.8,
      "win_probabilities": {
        "away_prob": 0.48,
        "home_prob": 0.52
      },
      "betting_recommendations": {
        "moneyline": {
          "pick": null,
          "team": null,
          "confidence": 0
        },
        "total_runs": {
          "line": 9.5,
          "pick": "over",
          "predicted_total": 10.8,
          "confidence": 0.541
        },
        "value_bets": [
          {
            "type": "total",
            "recommendation": "Over 9.5",
            "expected_value": 0.082,
            "win_probability": 0.5410526315789473,
            "american_odds": -110,
            "confidence": "medium",
            "predicted_total": 10.8,
            "betting_line": 9.5
          }
        ]
      },
      "overall_confidence": 0.541,
      "recommendation_quality": "MEDIUM"
    },
    "Chicago White Sox @ Kansas City Royals": {
      "away_team": "Chicago White Sox",
      "home_team": "Kansas City Royals",
      "away_pitcher": "Sean Burke",
      "home_pitcher": "Michael Lorenzen",
      "has_tbd_pitchers": false,
      "predicted_score": "5.2-5.6",
      "predicted_total_runs": 10.8,
      "win_probabilities": {
        "away_prob": 0.466,
        "home_prob": 0.534
      },
      "betting_recommendations": {
        "moneyline": {
          "pick": "home",
          "team": "Kansas City Royals",
          "confidence": 0.534
        },
        "total_runs": {
          "line": 9.5,
          "pick": "over",
          "predicted_total": 10.8,
          "confidence": 0.541
        },
        "value_bets": [
          {
            "type": "moneyline",
            "recommendation": "Kansas City Royals ML",
            "expected_value": 0.068,
            "win_probability": 0.534,
            "american_odds": 110,
            "confidence": "medium"
          },
          {
            "type": "total",
            "recommendation": "Over 9.5",
            "expected_value": 0.082,
            "win_probability": 0.5410526315789473,
            "american_odds": -110,
            "confidence": "medium",
            "predicted_total": 10.8,
            "betting_line": 9.5
          }
        ]
      },
      "overall_confidence": 0.541,
      "recommendation_quality": "MEDIUM"
    },
    "Detroit Tigers @ Minnesota Twins": {
      "away_team": "Detroit Tigers",
      "home_team": "Minnesota Twins",
      "away_pitcher": "Casey Mize",
      "home_pitcher": "Zebby Matthews",
      "has_tbd_pitchers": false,
      "predicted_score": "5.3-5.6",
      "predicted_total_runs": 10.8,
      "win_probabilities": {
        "away_prob": 0.461,
        "home_prob": 0.539
      },
      "betting_recommendations": {
        "moneyline": {
          "pick": "home",
          "team": "Minnesota Twins",
          "confidence": 0.539
        },
        "total_runs": {
          "line": 9.5,
          "pick": "over",
          "predicted_total": 10.8,
          "confidence": 0.541
        },
        "value_bets": [
          {
            "type": "moneyline",
            "recommendation": "Minnesota Twins ML",
            "expected_value": 0.078,
            "win_probability": 0.539,
            "american_odds": 110,
            "confidence": "medium"
          },
          {
            "type": "total",
            "recommendation": "Over 9.5",
            "expected_value": 0.082,
            "win_probability": 0.5410526315789473,
            "american_odds": -110,
            "confidence": "medium",
            "predicted_total": 10.8,
            "betting_line": 9.5
          }
        ]
      },
      "overall_confidence": 0.541,
      "recommendation_quality": "MEDIUM"
    },
    "New York Yankees @ St. Louis Cardinals": {
      "away_team": "New York Yankees",
      "home_team": "St. Louis Cardinals",
      "away_pitcher": "Max Fried",
      "home_pitcher": "Sonny Gray",
      "has_tbd_pitchers": false,
      "predicted_score": "3.5-3.6",
      "predicted_total_runs": 7.2,
      "win_probabilities": {
        "away_prob": 0.485,
        "home_prob": 0.515
      },
      "betting_recommendations": {
        "moneyline": {
          "pick": null,
          "team": null,
          "confidence": 0
        },
        "total_runs": {
          "line": 9.5,
          "pick": "under",
          "predicted_total": 7.2,
          "confidence": 0.573
        },
        "value_bets": [
          {
            "type": "total",
            "recommendation": "Under 9.5",
            "expected_value": 0.145,
            "win_probability": 0.5726315789473684,
            "american_odds": -110,
            "confidence": "medium",
            "predicted_total": 7.2,
            "betting_line": 9.5
          }
        ]
      },
      "overall_confidence": 0.573,
      "recommendation_quality": "MEDIUM"
    },
    "Arizona Diamondbacks @ Colorado Rockies": {
      "away_team": "Arizona Diamondbacks",
      "home_team": "Colorado Rockies",
      "away_pitcher": "Ryne Nelson",
      "home_pitcher": "Chase Dollander",
      "has_tbd_pitchers": false,
      "predicted_score": "5.3-5.5",
      "predicted_total_runs": 10.8,
      "win_probabilities": {
        "away_prob": 0.467,
        "home_prob": 0.533
      },
      "betting_recommendations": {
        "moneyline": {
          "pick": "home",
          "team": "Colorado Rockies",
          "confidence": 0.533
        },
        "total_runs": {
          "line": 9.5,
          "pick": "over",
          "predicted_total": 10.8,
          "confidence": 0.541
        },
        "value_bets": [
          {
            "type": "moneyline",
            "recommendation": "Colorado Rockies ML",
            "expected_value": 0.066,
            "win_probability": 0.533,
            "american_odds": 110,
            "confidence": "medium"
          },
          {
            "type": "total",
            "recommendation": "Over 9.5",
            "expected_value": 0.082,
            "win_probability": 0.5410526315789473,
            "american_odds": -110,
            "confidence": "medium",
            "predicted_total": 10.8,
            "betting_line": 9.5
          }
        ]
      },
      "overall_confidence": 0.541,
      "recommendation_quality": "MEDIUM"
    },
    "Tampa Bay Rays @ San Francisco Giants": {
      "away_team": "Tampa Bay Rays",
      "home_team": "San Francisco Giants",
      "away_pitcher": "Adrian Houser",
      "home_pitcher": "Justin Verlander",
      "has_tbd_pitchers": false,
      "predicted_score": "3.3-3.4",
      "predicted_total_runs": 6.7,
      "win_probabilities": {
        "away_prob": 0.473,
        "home_prob": 0.527
      },
      "betting_recommendations": {
        "moneyline": {
          "pick": "home",
          "team": "San Francisco Giants",
          "confidence": 0.527
        },
        "total_runs": {
          "line": 9.5,
          "pick": "under",
          "predicted_total": 6.7,
          "confidence": 0.588
        },
        "value_bets": [
          {
            "type": "moneyline",
            "recommendation": "San Francisco Giants ML",
            "expected_value": 0.054,
            "win_probability": 0.527,
            "american_odds": 110,
            "confidence": "medium"
          },
          {
            "type": "total",
            "recommendation": "Under 9.5",
            "expected_value": 0.177,
            "win_probability": 0.588421052631579,
            "american_odds": -110,
            "confidence": "medium",
            "predicted_total": 6.7,
            "betting_line": 9.5
          }
        ]
      },
      "overall_confidence": 0.588,
      "recommendation_quality": "MEDIUM"
    },
    "San Diego Padres @ Los Angeles Dodgers": {
      "away_team": "San Diego Padres",
      "home_team": "Los Angeles Dodgers",
      "away_pitcher": "Dylan Cease",
      "home_pitcher": "Blake Snell",
      "has_tbd_pitchers": false,
      "predicted_score": "3.3-3.5",
      "predicted_total_runs": 6.7,
      "win_probabilities": {
        "away_prob": 0.469,
        "home_prob": 0.531
      },
      "betting_recommendations": {
        "moneyline": {
          "pick": "home",
          "team": "Los Angeles Dodgers",
          "confidence": 0.531
        },
        "total_runs": {
          "line": 9.5,
          "pick": "under",
          "predicted_total": 6.7,
          "confidence": 0.588
        },
        "value_bets": [
          {
            "type": "moneyline",
            "recommendation": "Los Angeles Dodgers ML",
            "expected_value": 0.062,
            "win_probability": 0.531,
            "american_odds": 110,
            "confidence": "medium"
          },
          {
            "type": "total",
            "recommendation": "Under 9.5",
            "expected_value": 0.177,
            "win_probability": 0.588421052631579,
            "american_odds": -110,
            "confidence": "medium",
            "predicted_total": 6.7,
            "betting_line": 9.5
          }
        ]
      },
      "overall_confidence": 0.588,
      "recommendation_quality": "MEDIUM"
    },
    "Los Angeles Angels @ Athletics": {
      "away_team": "Los Angeles Angels",
      "home_team": "Athletics",
      "away_pitcher": "Tyler Anderson",
      "home_pitcher": "Luis Morales",
      "has_tbd_pitchers": false,
      "predicted_score": "4.2-4.4",
      "predicted_total_runs": 8.6,
      "win_probabilities": {
        "away_prob": 0.478,
        "home_prob": 0.522
      },
      "betting_recommendations": {
        "moneyline": {
          "pick": "home",
          "team": "Athletics",
          "confidence": 0.522
        },
        "total_runs": {
          "line": 9.5,
          "pick": "under",
          "predicted_total": 8.6,
          "confidence": 0.528
        },
        "value_bets": [
          {
            "type": "moneyline",
            "recommendation": "Athletics ML",
            "expected_value": 0.044,
            "win_probability": 0.522,
            "american_odds": 110,
            "confidence": "medium"
          },
          {
            "type": "total",
            "recommendation": "Under 9.5",
            "expected_value": 0.057,
            "win_probability": 0.5284210526315789,
            "american_odds": -110,
            "confidence": "medium",
            "predicted_total": 8.6,
            "betting_line": 9.5
          }
        ]
      },
      "overall_confidence": 0.528,
      "recommendation_quality": "MEDIUM"
    }
  },
  "summary": {
    "total_games": 15,
    "moneyline_picks": 13,
    "over_picks": 8,
    "under_picks": 7,
    "high_confidence_picks": 0
  }
}